cryptopayclient/__init__.py
cryptopayclient/cryptopayclient.py
cryptopayclient-0.1.dist-info/LICENSE
cryptopayclient-0.1.dist-info/METADATA
cryptopayclient-0.1.dist-info/WHEEL
cryptopayclient-0.1.dist-info/top_level.txt
cryptopayclient-0.1.dist-info/RECORD
