Metadata-Version: 2.1
Name: cryptopayclient
Version: 0.1
Summary: API for CryptoBot
Home-page: https://github.com/andrewzaycew/cryptopayclient
Author: Andrew Zaycev
Author-email: bonyxyq@gmail.com
License: MIT
Project-URL: Bug Tracker, https://github.com/andrewzaycew/cryptopayclient/issues
Classifier: Intended Audience :: Developers
Classifier: License :: OSI Approved :: MIT License
Classifier: Operating System :: OS Independent
Classifier: Programming Language :: Python :: 3
Classifier: Topic :: Software Development :: Libraries :: Python Modules
Requires-Python: >=3.6
License-File: LICENSE
Requires-Dist: requests
